sql_orm/__init__.py
sql_orm/postgresql/__init__.py
sql_orm/postgresql/datatypes.py
sql_orm/postgresql/objects.py
sql_orm/postgresql/tables.py
sql_orm/postgresql/sql/__init__.py
sql_orm-1.2.2.dist-info/LICENSE
sql_orm-1.2.2.dist-info/METADATA
sql_orm-1.2.2.dist-info/WHEEL
sql_orm-1.2.2.dist-info/top_level.txt
sql_orm-1.2.2.dist-info/RECORD
