Metadata-Version: 2.1
Name: sql-orm
Version: 1.2.2
Summary: A python based ORM (Object relational mapping) to make flexible queries and saving new items in the database.
Home-page: https://github.com/shubhamdipt/sql-orm
Author: Shubham Dipt
Author-email: shubham.dipt@gmail.com
License: MIT
Platform: any
Classifier: Programming Language :: Python :: 3
Classifier: License :: OSI Approved :: MIT License
Classifier: Operating System :: OS Independent
